{
    "day_sin": "float32",
    "day_cos": "float32",
    "pair_AUDJPY": "int64",
    "pair_AUDUSD": "int64",
    "pair_CHFJPY": "int64",
    "pair_EURCAD": "int64",
    "pair_EURCHF": "int64",
    "pair_EURGBP": "int64",
    "pair_EURJPY": "int64",
    "pair_EURSEK": "int64",
    "pair_EURUSD": "int64",
    "pair_GBPCHF": "int64",
    "pair_GBPJPY": "int64",
    "pair_GBPUSD": "int64",
    "pair_NZDUSD": "int64",
    "pair_USDCAD": "int64",
    "pair_USDCHF": "int64",
    "pair_USDJPY": "int64",
    "pair_USDNOK": "int64",
    "pair_USDSEK": "int64",
    "pair_USDSGD": "int64",
    "pair_USDZAR": "int64",
    "pair_CADJPY": "int64",
    "pair_EURAUD": "int64",
    "pair_EURNOK": "int64",
    "pair_AUDCAD": "int64",
    "pair_AUDCHF": "int64",
    "pair_CADCHF": "int64",
    "pair_EURNZD": "int64",
    "pair_GBPAUD": "int64",
    "pair_GBPCAD": "int64",
    "pair_GBPNZD": "int64",
    "pair_NZDCAD": "int64",
    "pair_NZDCHF": "int64",
    "pair_NZDJPY": "int64",
    "pair_AUDNZD": "int64",
    "pair_AUDSGD": "int64",
    "pair_EURSGD": "int64",
    "pair_USDMXN": "int64",
    "pair_USDPLN": "int64",
    "pair_EURHUF": "int64",
    "pair_USDHUF": "int64",
    "pair_EURMXN": "int64",
    "pair_GBPMXN": "int64",
    "pair_GBPSGD": "int64",
    "pair_GBPZAR": "int64",
    "pair_EURZAR": "int64"
}